{
    "总院住院费用表-挂号日期数量": "统计“总院住院费用表”中“charge_time”字段的记录数量，反映挂号日期的总次数。",
    "十梓街住院费用表-挂号日期数量": "统计“十梓街住院费用表”中“charge_time”字段的记录数量，反映挂号日期的数量。",
    "总院住院费用表-总院住院人数": "统计“总院住院费用表”中“inpatient_no”字段的记录数量，反映总院住院人数。",
    "总院住院费用表-总院总费用": "总院住院费用表-总院总费用：计算总院住院费用表中total_charge字段的数值总和。",
    "总院住院费用表-总费用平均": "总院住院费用表-总费用平均：计算总院住院费用表中total_charge字段的平均值。",
    "总院住院费用表-总费用最小值": "在“总院住院费用表”中，“总费用最小值”指“total_charge”字段中的最小数值。",
    "总院住院费用表-总费用最大值": "在“总院住院费用表”中，“总费用最大值”指列“total_charge”中的最大数值。",
    "总院住院费用表-费用数量": "统计“总院住院费用表”中“charge_fee”字段的记录数量。",
    "总院住院费用表-病区名称数量": "统计“总院住院费用表”中“ward_name”字段的记录数量",
    "总院住院费用表-病区编码数量": "统计“总院住院费用表”中“ward_code”字段的记录数量",
    "总院住院费用表-费用项目名称数量": "统计“总院住院费用表”中“item_name”字段的记录数量，反映费用项目名称的数量。",
    "总院住院费用表-科室名称数量": "统计“总院住院费用表”中“dept_name”字段的记录数量",
    "总院住院费用表-科室编码数量": "统计“总院住院费用表”中“dept_code”字段的记录数量，反映科室编码的总数。",
    "总院住院费用表-患者姓名数量": "统计“总院住院费用表”中“name”字段的记录数量，反映患者姓名的总数。",
    "十梓街住院费用表-十梓街住院人数": "统计“十梓街住院费用表”中“inpatient_no”字段的记录数量，反映十梓街住院人数。",
    "十梓街住院费用表-十梓街总费用": "十梓街住院费用表-十梓街总费用，指计算“十梓街住院费用表”中“total_charge”字段的数值总和。",
    "十梓街住院费用表-总费用平均": "计算“十梓街住院费用表”中“total_charge”字段的平均值，反映住院费用的平均水平。",
    "十梓街住院费用表-总费用最小值": "在“十梓街住院费用表”中，“总费用最小值”指的是“total_charge”字段中数值最小的一个。",
    "十梓街住院费用表-总费用最大值": "在“十梓街住院费用表”中，“总费用最大值”指的是列“total_charge”中的最大数值。",
    "十梓街住院费用表-费用数量": "统计“十梓街住院费用表”中“charge_fee”字段的记录数量",
    "十梓街住院费用表-病区名称数量": "统计“十梓街住院费用表”中“ward_name”字段的记录数量",
    "十梓街住院费用表-病区编码数量": "统计“十梓街住院费用表”中“ward_code”字段的记录数量",
    "十梓街住院费用表-费用项目名称数量": "统计“十梓街住院费用表”中“item_name”字段的记录数量",
    "十梓街住院费用表-科室名称数量": "统计“十梓街住院费用表”中“dept_name”字段的记录数量",
    "十梓街住院费用表-科室编码数量": "统计“十梓街住院费用表”中“dept_code”字段的记录数量，反映该表中不同科室编码的数量。",
    "十梓街住院费用表-患者姓名数量": "统计“十梓街住院费用表”中“name”字段的记录数量，反映患者姓名的数量。",
    "病案首页基本信息表-病案号数量": "统计“病案首页基本信息表”中“fmrdid”字段的记录数量，反映病案首页基本信息表中的病案号数量。",
    "病案首页基本信息表-住院人数": "统计“病案首页基本信息表”中“fbihid”的记录数量，反映住院人数。",
    "病案首页基本信息表-主治医师数量": "统计“病案首页基本信息表”中“fzzys”字段的记录数量，反映主治医师的数量。",
    "病案首页基本信息表-住院医师数量": "统计“病案首页基本信息表”中字段“fzyys”（住院医师数量）的记录数量。",
    "病案首页基本信息表-主任医师数量": "统计“病案首页基本信息表”中字段“fzrys”记录的数量，反映主任医师的数量。",
    "病案首页基本信息表-质控医生数量": "统计“病案首页基本信息表”中“fzkys”字段的记录数量，反映质控医生的数量。",
    "病案首页基本信息表-质控护士数量": "统计“病案首页基本信息表”中字段“fzkhs”的记录数量，反映质控护士的数量。",
    "病案首页基本信息表-科室数量": "统计“病案首页基本信息表”中“fioffi”的记录数量，反映科室数量。",
    "病案首页基本信息表-入院病房编码数量": "统计“病案首页基本信息表”中字段“filoca”的记录数量，反映入院病房编码的数量。",
    "病案首页基本信息表-转入科室编码数量": "统计“病案首页基本信息表”中“ftoffi”字段的记录数量，反映转入科室编码的数量。",
    "病案首页基本信息表-转入病房编码数量": "统计“病案首页基本信息表”中“ftloca”字段的记录数量，反映转入病房编码的数量。",
    "病案首页基本信息表-再转科室编码数量": "统计“病案首页基本信息表”中“froffi”字段的记录数量，反映再转科室编码的数量。",
    "病案首页基本信息表-再转病房编码数量": "统计“病案首页基本信息表”中字段“frloca”的记录数量，反映再转病房编码的数量。",
    "病案首页基本信息表-出院科室编码数量": "统计“病案首页基本信息表”中“fooffi”字段的记录数量，反映出院科室编码的数量。",
    "病案首页基本信息表-出院病房编码数量": "统计“病案首页基本信息表”中“foloca”字段的记录数量，反映出院病房编码的数量。",
    "病案首页基本信息表-入院时间数量": "统计“病案首页基本信息表”中“fihdat”字段的记录数量，反映入院时间的数据条目总数。",
    "病案首页基本信息表-出院时间数量": "统计“病案首页基本信息表”中“fodate”字段的记录数量，反映出院时间的数据条目总数。",
    "病案首页基本信息表-转入日期数量": "统计“病案首页基本信息表”中“ftdate”字段的记录数量",
    "病案首页基本信息表-死亡日期数量": "统计“病案首页基本信息表”中“fswdat”字段的记录数量，即为病案首页基本信息表中死亡日期的数量。",
    "病案首页基本信息表-患者姓名数量": "统计“病案首页基本信息表”中“fname”字段的记录数量，反映患者姓名的数量。",
    "病案首页基本信息表-患者性别数量": "统计“病案首页基本信息表”中“fsex”字段的记录数量，反映患者性别的数量分布。",
    "病案首页基本信息表-入院诊断数量": "统计“病案首页基本信息表”中“fryzd”字段的记录数量，反映入院诊断的数量。",
    "病案首页基本信息表-门（急）诊诊断数量": "统计“病案首页基本信息表”中“fmzzd”字段的记录数量，反映门（急）诊诊断的数量。",
    "病案首页诊断信息表-病案号数量": "统计“病案首页诊断信息表”中“fmrdid”字段的记录数量，反映病案首页诊断信息表中病案号的总数。",
    "病案首页诊断信息表-诊断数量": "统计“病案首页诊断信息表”中“ficd_desc”字段的记录数量，反映诊断信息的全面性与详细程度。",
    "病案首页基本信息表-住院天数": "计算病案首页基本信息表中“fbihda”字段的数值总和，反映住院天数的累计值。",
    "模糊查询关联维度测试-关联环境编号数量": "针对“模糊查询关联维度测试-关联环境编号数量”这一指标，其意在统计“模糊查询关联维度测试”中“id4”字段的记录总数。",
    "模糊查询关联维度测试-关联环境时间数量": "针对“模糊查询关联维度测试-关联环境时间数量”这一指标，其意在统计“模糊查询关联维度测试”场景下“app_time4”字段的记录总数。",
    "模糊查询关联维度测试-关联环境编码数量": "针对“模糊查询关联维度测试-关联环境编码数量”这一指标，其意在统计“模糊查询关联维度测试”场景下，“test_code4”字段的记录总数。",
    "模糊查询关联维度测试-关联环境名称数量": "针对“模糊查询关联维度测试-关联环境名称数量”这一指标，其意在统计“模糊查询关联维度测试”中特定标识“test_name4”的记录总数。",
    "模糊查询关联维度测试-关联环境标识数量": "针对“模糊查询关联维度测试-关联环境标识数量”这一指标，其定义为统计在“模糊查询关联维度测试”中“test_flow4”记录的数量。",
    "模糊查询关联维度测试-关联环境状态合计": "针对“模糊查询关联维度测试-关联环境状态合计”这一指标，其意在计算“模糊查询关联维度测试”中“test_status4”数值的总和。",
    "模糊查询关联维度测试-关联环境状态平均": "针对“模糊查询关联维度测试-关联环境状态平均”这一指标，其计算方法为在“模糊查询关联维度测试”中，对“test_status4”字段的值进行平均计算。",
    "模糊查询关联维度测试-关联环境状态最大值": "在“模糊查询关联维度测试”中，指标关注于列“test_status4”中的最大数值，以此来评估关联环境状态的最大值。",
    "模糊查询关联维度测试1-关联业务域环境编号数量": "针对“模糊查询关联维度测试1-关联业务域环境编号数量”这一指标，其含义为统计“模糊查询关联维度测试1”中标识为“id5”的记录数量。",
    "模糊查询关联维度测试1-关联业务域环境时间数量": "针对“模糊查询关联维度测试1-关联业务域环境时间数量”这一指标，其目的在于统计“模糊查询关联维度测试1”中“app_time5”字段的记录数量。",
    "模糊查询关联维度测试1-关联业务域环境编码数量": "针对“模糊查询关联维度测试1”进行统计，记录数量为“test_code5”出现的次数。",
    "模糊查询关联维度测试1-关联业务域环境名称数量": "针对“模糊查询关联维度测试1-关联业务域环境名称数量”这一指标，其意在统计“模糊查询关联维度测试1”中“test_name5”字段的记录总数。",
    "模糊查询关联维度测试1-关联业务域环境标识数量": "针对“模糊查询关联维度测试1-关联业务域环境标识数量”这一指标，其意在统计“模糊查询关联维度测试1”中特定标识“test_flow5”的记录数量。",
    "模糊查询关联维度测试1-关联业务域环境状态合计": "模糊查询关联维度测试1-关联业务域环境状态合计，计算“模糊查询关联维度测试1”中“test_status5”的数值总和。",
    "模糊查询关联维度测试1-关联业务域环境状态平均": "针对“模糊查询关联维度测试1-关联业务域环境状态平均”这一指标，其计算方法为在“模糊查询关联维度测试1”中，对“test_status5”字段的值进行平均计算。",
    "模糊查询关联维度测试1-关联业务域环境状态最小值": "在“模糊查询关联维度测试1”中，指标关注的是“test_status5”的最小值。",
    "模糊查询关联维度测试1-关联业务域环境状态最大值": "在“模糊查询关联维度测试1”中，指标关注的是列“test_status5”中的最大数值，以此来反映关联业务域环境状态的最大值。",
    "模糊查询关联维度测试2-上游关联业务域环境编号数量": "针对“模糊查询关联维度测试2-上游关联业务域环境编号数量”这一指标，其含义为统计“模糊查询关联维度测试2”中与“id6”相关的记录数量。",
    "模糊查询关联维度测试2-上游关联业务域环境时间数量": "针对“模糊查询关联维度测试2-上游关联业务域环境时间数量”这一指标，其意在统计“模糊查询关联维度测试2”中“app_time6”字段的记录数量。",
    "模糊查询关联维度测试2-上游关联业务域环境编码数量": "针对“模糊查询关联维度测试2-上游关联业务域环境编码数量”这一指标，其意在统计“模糊查询关联维度测试2”中“test_code6”字段的记录总数。",
    "模糊查询关联维度测试2-上游关联业务域环境名称数量": "针对“模糊查询关联维度测试2-上游关联业务域环境名称数量”这一指标，其意在统计“模糊查询关联维度测试2”中“test_name6”字段的记录总数。",
    "模糊查询关联维度测试2-上游关联业务域环境标识数量": "针对“模糊查询关联维度测试2-上游关联业务域环境标识数量”这一指标，其定义为统计“模糊查询关联维度测试2”中“test_flow6”记录的数量。",
    "模糊查询关联维度测试2-上游关联业务域环境状态合计": "模糊查询关联维度测试2-上游关联业务域环境状态合计，指计算“模糊查询关联维度测试2”中“test_status6”数值的总和。",
    "模糊查询关联维度测试2-上游关联业务域环境状态平均": "针对“模糊查询关联维度测试2-上游关联业务域环境状态平均”这一指标，其意在评估“模糊查询关联维度测试2”中“test_status6”数值的平均水平。",
    "模糊查询关联维度测试2-上游关联业务域环境状态最小值": "在“模糊查询关联维度测试2”中，指标关注的是“test_status6”的最小值，即在相关业务域环境中，寻找“test_status6”这一状态的最小数值。",
    "模糊查询关联维度测试2-上游关联业务域环境状态最大值": "在“模糊查询关联维度测试2”中，指标关注的是“test_status6”列中的最大数值，反映上游关联业务域环境状态的最大值。",
    "门诊检验申请-申请人编码数量": "门诊检验申请-申请人编码数量指标用于统计门诊检验申请中applier_id字段的记录数量。",
    "门诊检验申请-申请人数量": "门诊检验申请-申请人数量指标用于统计门诊检验申请中申请人（applier）的记录数量。",
    "门诊检验申请-检查编号数量": "门诊检验申请-检查编号数量 指的是统计门诊检验申请中“opid”字段的记录数量。",
    "门诊检验申请-申请时间数量": "门诊检验申请-申请时间数量指标用于统计门诊检验申请中apply_date_time字段的记录数量。",
    "门诊检验申请-科室编码数量": "门诊检验申请-科室编码数量指标用于统计门诊检验申请中科室编码（dept_code）的记录数量。",
    "门诊检验申请-科室名称数量": "门诊检验申请-科室名称数量 指的是统计门诊检验申请中科室名称的记录数量。",
    "门诊检验申请-申请标识数量": "门诊检验申请-申请标识数量通过统计“门诊检验申请”中“exam_apply_flow”字段的记录数量来衡量门诊检验申请的申请标识总数。",
    "门诊检验申请-检查状态数量": "门诊检验申请-检查状态数量指标用于统计门诊检验申请中exam_status字段的记录数量。",
    "门诊检验申请-检验类型名称数量": "门诊检验申请-检验类型名称数量 指标用于统计门诊检验申请中不同检验类型名称的记录数量。",
    "门诊检验申请-检验类型编码数量": "门诊检验申请中，统计exam_code字段的记录数量，反映不同检验类型编码的多样性。",
    "住院检验申请-申请人编码数量": "住院检验申请-申请人编码数量统计的是“住院检验申请”记录中“applier_id”字段的记录数量。",
    "住院检验申请-申请人数量": "住院检验申请-申请人数量指标用于统计住院检验申请中申请人（applier）的记录数量。",
    "住院检验申请-检查编号数量": "住院检验申请-检查编号数量通过统计住院检验申请中ipid的记录数量来衡量。",
    "住院检验申请-申请时间数量": "住院检验申请-申请时间数量指标用于统计住院检验申请中apply_date_time字段的记录数量。",
    "住院检验申请-科室编码数量": "住院检验申请-科室编码数量指标用于统计住院检验申请中科室编码（dept_code）的记录数量。",
    "住院检验申请-科室名称数量": "住院检验申请-科室名称数量指标用于统计住院检验申请中不同科室名称的记录数量。",
    "住院检验申请-申请标识数量": "住院检验申请-申请标识数量通过统计“住院检验申请”中“exam_apply_flow”字段的记录数量来衡量。",
    "住院检验申请-检查状态数量": "住院检验申请-检查状态数量指标用于统计住院检验申请中exam_status字段的记录数量。",
    "住院检验申请-检验类型名称数量": "住院检验申请中，统计exam_name字段的记录数量，反映不同检验类型名称的数量。",
    "住院检验申请-检验类型编码数量": "住院检验申请中，统计exam_code字段的记录数量，反映住院期间检验申请的检验类型编码多样性。",
    "测试表1-测试编号数量": "测试表1-测试编号数量：统计测试表1中id字段的记录总数。",
    "测试表1-测试时间数量": "测试表1-测试时间数量：统计测试表1中app_time字段的记录数量。",
    "测试表1-测试数量": "测试表1-测试数量：统计测试表1中test_code字段的记录数量。",
    "测试表1-测试名称数量": "测试表1-测试名称数量：统计“测试表1”中“test_name”字段的记录数量。",
    "测试表1-测试标识数量": "测试表1-测试标识数量：统计“测试表1”中“test_flow”字段的记录数量。",
    "测试表1-测试状态合计": "测试表1-测试状态合计：计算测试表1中test_status字段的数值总和。",
    "测试表1-测试状态平均": "测试表1-测试状态平均：计算测试表1中test_status字段的平均值。",
    "测试表1-测试状态最小值": "测试表1中的测试状态最小值为“test_status”列中找到的最小数值。",
    "测试表1-测试状态最大值": "测试表1中的测试状态最大值为“test_status”列中找到的最大数值。",
    "测试表2-测试编号数量": "测试表2-测试编号数量：统计测试表2中id字段的记录总数。",
    "测试表2-测试时间数量": "测试表2-测试时间数量：统计测试表2中app_time字段的记录数量。",
    "测试表2-测试编码数量": "测试表2-测试编码数量：统计测试表2中test_code字段的记录数量。",
    "测试表2-测试名称数量": "测试表2-测试名称数量：统计“测试表2”中“test_name”字段的记录数量。",
    "测试表2-测试标识数量": "测试表2-测试标识数量：统计“测试表2”中“test_flow”字段的记录数量。",
    "测试表2-测试状态合计": "测试表2-测试状态合计通过计算“测试表2”中“test_status”字段的数值总和来反映测试状态的总体情况。",
    "测试表2-测试状态平均": "测试表2-测试状态平均：计算测试表2中test_status字段的平均值。",
    "测试表2-测试状态最小值": "测试表2中，test_status字段的最小值表示在该表范围内，test_status所能取到的最小数值。",
    "测试表2-测试状态最大值": "测试表2中，查找test_status列的最大数值，以此确定测试状态的最大值。",
    "病案首页手术信息表-手术人数": "统计“病案首页手术信息表”中“fmrdid”字段的记录数量，反映手术人数。",
    "病案首页手术信息表-手术日期数量": "统计“病案首页手术信息表”中“fopdat”字段的记录数量，反映手术日期的统计情况。",
    "病案首页手术信息表-手术等级数量": "统计“病案首页手术信息表”中“fopid”字段的记录数量，反映手术等级的数量。",
    "病案首页手术信息表-手术科室数量": "统计“病案首页手术信息表”中“fopoffi”字段的记录数量，反映手术涉及的科室数量。",
    "病案首页手术信息表-手术医师数量": "统计“病案首页手术信息表”中“fopdoc”字段的记录数量，反映手术医师数量。",
    "病案首页手术信息表-愈合等级数量": "统计“病案首页手术信息表”中“fyyp”字段的记录数量，用于反映愈合等级数量。",
    "病案首页手术信息表-手术部位感染数量": "统计“病案首页手术信息表”中“fssbwgr”字段的记录数量，反映手术部位感染数量。",
    "病案首页手术信息表-是否有手术并发症数量": "统计“病案首页手术信息表”中“fssbfz”字段的记录数量，反映是否有手术并发症的情况。",
    "病案首页手术信息表-手术并发症名称数量": "统计“病案首页手术信息表”中“fs06”字段的记录数量，反映手术并发症名称的数量。",
    "病案首页手术信息表-手术并发症数量": "从“病案首页手术信息表”中筛选出“fmrdid”等于“有”的记录，然后对这些记录中的“fmrdid”字段进行计数，以得出手术并发症的数量。",
    "住院工作量-日期数量": "住院工作量-日期数量指标用于统计住院工作量中特定字段\"fdate\"的记录数量。",
    "住院工作量-科室数量": "住院工作量-科室数量指标用于统计“住院工作量”中“foffi”记录的数量。",
    "住院工作量-原有人数数量": "住院工作量-原有人数数量通过统计“住院工作量”中“fyyrs”字段的记录数量来衡量。",
    "住院工作量-入院人数数量": "住院工作量-入院人数数量通过统计“住院工作量”中“fryrs”的记录数量来衡量。",
    "住院工作量-转入人数数量": "住院工作量-转入人数数量通过统计“住院工作量”中“fzrrs”字段的记录数量来衡量转入的患者人数。",
    "住院工作量-转出人数数量": "住院工作量-转出人数数量通过统计“住院工作量”中“fzcrs”字段的记录数量来衡量。",
    "住院工作量-出院人数合计": "住院工作量-出院人数合计通过汇总“住院工作量”中“fcyrsj”字段的数值来计算得出。",
    "住院工作量-出院人数平均": "住院工作量-出院人数平均通过计算住院工作量中“fcyrsj”指标的平均值来反映一定时期内平均每日或定期的出院人数。",
    "住院工作量-出院人数最小值": "住院工作量指标中的出院人数最小值，即在住院工作量数据中查找“fcyrsj”字段的最小数值。",
    "住院工作量-出院人数最大值": "住院工作量指标通过分析“fcyrsj”列的数据，确定出院人数的最大值。",
    "住院工作量-占用总床日数合计": "住院工作量-占用总床日数合计通过计算住院工作量中“fzycw”项的数值总和来反映医疗机构在一定时期内因住院治疗而占用的总床日数。",
    "住院工作量-占用总床日数平均": "住院工作量-占用总床日数平均通过计算住院工作量中“fzycw”项的平均值来反映住院期间总床日数的平均水平。",
    "住院工作量-占用总床日数最小值": "在住院工作量的统计中，占用总床日数最小值即为“fzycw”这一字段中找到的最小数值。",
    "住院工作量-占用总床日数最大值": "住院工作量指标通过分析列“fzycw”来确定占用总床日数的最大值。",
    "住院工作量-现有人数数量": "住院工作量-现有人数数量指标用于统计住院工作量中“fxyrs”字段的记录数量。",
    "住院工作量-其中病危数数量": "住院工作量中的病危数数量通过统计“fxyrsw”字段的记录数量来衡量。",
    "住院工作量-手术数合计": "住院工作量-手术数合计通过汇总“住院工作量”中“fssrs”项的数值总和来计算得出。",
    "住院工作量-手术数平均": "住院工作量-手术数平均通过计算住院工作量中“fssrs”值的平均来衡量。",
    "住院工作量-手术数最小值": "在住院工作量的统计中，寻找“fssrs”这一分类下的最小手术数量值。",
    "住院工作量-手术数最大值": "住院工作量指标中的手术数最大值指在“住院工作量”数据集中，“fssrs”列中数值的最大值。",
    "住院工作量-开放床数合计": "住院工作量-开放床数合计通过计算“住院工作量”中“fkfcs”项的数值总和来反映医院在一定时期内开放床位的总数量。",
    "住院工作量-开放床数平均": "住院工作量-开放床数平均通过计算住院工作量中“fkfcs”数值的平均值来反映开放床位的平均水平。",
    "住院工作量-开放床数最小值": "在住院工作量的统计中，指标关注的是“fkfcs”这一项，具体表现为开放床数的最小值。",
    "住院工作量-开放床数最大值": "住院工作量指标通过分析“住院工作量”中的相关数据，确定列“fkfcs”所代表的开放床数中的最大值，以此反映住院工作量中的床位使用峰值。",
    "住院工作量-实际占用床位数合计": "住院工作量-实际占用床位数合计通过汇总“住院工作量”中“fsjcs”项的数值总和来计算得出。",
    "住院工作量-实际占用床位数平均": "住院工作量-实际占用床位数平均通过计算住院工作量中“fsjcs”各项数值的平均值来反映实际平均占用的床位数量。",
    "住院工作量-实际占用床位数最小值": "在住院工作量的统计中，实际占用床位数最小值即为“fsjcs”字段中找到的最小数值。",
    "住院工作量-实际占用床位数最大值": "住院工作量指标通过分析“fsjcs”列的数据，确定了实际占用床位数的最大值。",
    "住院工作量-其中临时加床数量": "住院工作量中的临时加床数量通过统计“fsjcsj”字段的记录数量来衡量。",
    "住院工作量-借他科数量": "住院工作量-借他科数量指标用于统计住院工作量中“fsjcst”类型的记录数量。",
    "住院工作量-本日空床数量": "住院工作量-本日空床数量指标用于统计“住院工作量”中“fbrkc”字段的记录数量，反映当日空置床位的总数。",
    "住院工作量-其中暂停使用数量": "住院工作量-其中暂停使用数量，指统计住院工作量中状态标记为“fbrkct”的记录数量。",
    "住院工作量-借给他科数量": "住院工作量-借给他科数量指标用于统计住院工作量中“fbrkcj”字段的记录数量。",
    "科室字典表-科室名称数量": "统计“科室字典表”中“dept_name”字段的记录数量，反映科室名称的总数。",
    "科室字典表-科室编码数量": "统计“科室字典表”中“dept_code”字段的记录数量，反映科室编码的总数。",
    "主键合计": "计算表\"HOSP_INFOR\"中字段\"id\"的数值总和，作为主键合计指标值。",
    "主键平均": "主键平均值通过计算表\"HOSP_INFOR\"中列\"id\"的所有值的总和，然后除以该列的记录数来得出。",
    "主键最小值": "在\"HOSP_INFOR\"中查找\"id\"字段的最小值。",
    "主键最大值": "在\"HOSP_INFOR\"表中，查找\"id\"列中的最大数值。",
    "-医院名称数量": "统计\"HOSP_INFOR\"表中\"fixmedins_name\"字段的记录数量，反映医院名称的数量。",
    "-医院等级数量": "统计\"HOSP_INFOR\"表中\"hosplv\"字段的记录数量，反映医院等级的数量分布。",
    "-医院地址数量": "统计\"HOSP_INFOR\"表中\"hosps_addr\"字段的记录数量，反映医院地址的数量。",
    "-医院性质数量": "统计\"HOSP_INFOR\"表中\"hospital_type\"字段的记录数量，反映不同性质医院的数量分布。",
    "病案首页基本信息表-出院人数": "从“病案首页基本信息表”中筛选出“fmrdid”不等于空值的所有记录，然后统计这些记录中“fmrdid”的数量，以此来计算出院人数。",
    "病案首页基本信息表-急诊人次": "从“病案首页基本信息表”中筛选出“fmrdid”字段值为“急诊”的记录，然后对这些记录中的“fmrdid”字段进行计数，以得出急诊人次的统计结果。",
    "病案首页基本信息表-门诊人次": "从“病案首页基本信息表”中筛选出“fmrdid”不等于空值的数据集，并对筛选后的数据集中“fmrdid”字段进行计数，以得出门诊人次的统计结果。",
    "病案首页基本信息表-低龄住院人数": "从“病案首页基本信息表”中筛选出“fbihid”小于18的记录，然后对这些记录中的“fbihid”进行计数，以得出低龄住院人数。",
    "病案首页手术信息表-手术并发症数": "从“病案首页手术信息表”中筛选出“fmrdid”等于“有”的记录，然后对这些记录中的“fmrdid”字段进行计数，以得出手术并发症的数量。",
    "病案首页基本信息表-急诊留观人次": "从“病案首页基本信息表”中筛选出“fmrdid”字段值为“急诊留观”的记录，然后对这些记录中的“fmrdid”字段进行计数，以得出急诊留观人次的统计结果。",
    "病案首页基本信息表-急诊室人次": "从“病案首页基本信息表”中筛选出“fmrdid”字段值为“抢救”的记录，然后对这些记录中的“fmrdid”字段进行计数，以得出急诊室人次的统计结果。",
    "住院检验申请-住院检验申请人次": "住院检验申请人次通过统计数据集中“applier_id”的数量来反映住院期间发起的检验申请次数。",
    "门诊检验申请-门诊检验申请人次": "门诊检验申请人次通过统计数据集中“applier_id”的数量来反映门诊检验申请的频次。",
    "测试表1-相同表结构功能测试指标": "测试表1-相同表结构功能测试指标用于统计数据集中“id”字段的总数，实现对特定数据集内唯一标识符的计数功能。",
    "总院住院费用表-西药费": "从“总院住院费用表”中筛选出total_charge等于西药费的所有记录，然后对这些记录中的total_charge字段值进行汇总计算。",
    "总院住院费用表-手术费": "从“总院住院费用表”中筛选出total_charge等于手术费的记录，然后对这些记录中的total_charge字段值进行汇总计算。",
    "总院住院费用表-床位费": "从“总院住院费用表”中筛选出total_charge等于床位费的记录，然后对这些记录中的total_charge字段值进行汇总计算。",
    "总院住院费用表-中草药费": "从“总院住院费用表”中筛选出total_charge等于中草药的记录，然后对这些记录中的total_charge字段值进行汇总计算。",
    "总院住院费用表-中成药费": "从“总院住院费用表”中筛选出total_charge等于中成药费的记录，然后对这些记录中的total_charge字段值进行汇总计算。",
    "十梓街住院费用表-西药费": "查询“十梓街住院费用表”中，total_charge 等于 西药费的记录，对这些记录中的“total_charge”字段值进行合计。",
    "十梓街住院费用表-床位费": "查询“十梓街住院费用表”中，total_charge 等于 床位费 的记录，对这些记录中的 total_charge 字段值进行合计。",
    "十梓街住院费用表-中成药费": "从“十梓街住院费用表”中筛选出total_charge等于中成药的记录，然后对这些记录中的total_charge字段值进行汇总计算。",
    "十梓街住院费用表-中草药费": "查询“十梓街住院费用表”中，total_charge 等于 中草药费的记录，对这些记录中的“total_charge”字段值进行合计。",
    "十梓街住院费用表-手术费": "查询“十梓街住院费用表”中，total_charge 等于 手术费的记录，对这些记录中的“total_charge”字段值进行合计。",
    "病案首页基本信息表-四级手术人数cs": "从“病案首页基本信息表”中筛选出“fmrdid”等于4的记录，然后对这些记录中的“fmrdid”进行计数，以得出四级手术的人数。",
    "测试表1-测试状态": "测试表1-测试状态：查询“测试表1”中id不等于1的数据集，并对数据集中“id”的数量进行计数。",
    "病案首页基本信息表-微创人数": "统计数据集中“fmrdid”字段的记录数量，以确定病案首页基本信息表中的微创手术人数。",
    "总院住院费用表-耗材费": "从“总院住院费用表”中筛选出total_charge等于材料费的记录，然后对这些记录中的total_charge字段值进行汇总计算。",
    "病案首页诊断信息表-死亡人数": "从“病案首页诊断信息表”中筛选出“fmrdid”字段值为“死亡”的记录，然后对这些记录中的“fmrdid”字段进行计数，以得出符合特定条件的死亡人数。",
    "病案首页基本信息表-测试情况占比": "病案首页基本信息表中的测试情况占比通过汇总数据集中“fmrdid”字段的记录数来计算。",
    "病案首页基本信息表-测试情况占": "病案首页基本信息表-测试情况占指标通过汇总数据集中“fmrdid”字段的值来计算。",
    "总院住院费用表-住院总费用": "总院住院费用表-住院总费用 指标计算为西药费、手术费、床位费、中草药费、中成药费及耗材费各项费用之和，其中每一项费用若为空则默认为0。",
    "病案首页手术信息表-手术并发症发生率": "病案首页手术信息表中的手术并发症发生率通过将病案首页手术信息表中记录的手术并发症数量除以病案首页手术信息表中的手术人数来计算得出。",
    "病案首页基本信息表-实际手术占比测试": "病案首页基本信息表中的实际手术占比通过将病案首页基本信息表中四级手术人数除以病案首页基本信息表中的出院人数来计算得出。",
    "病案首页基本信息表-四级占比": "病案首页基本信息表中四级手术人数与出院人数的比例，用于衡量医疗机构开展高难度手术的比例。",
    "总院住院费用表-药费占比": "总院住院费用表中的药费占比通过将西药费、中草药费和中成药费的总和除以总院总费用来计算，其中各项费用若为空则默认为0。",
    "总院住院费用表-耗材费占比": "总院住院费用中耗材费占比通过将住院期间使用的耗材费用除以住院期间的总费用来计算，若分母或分子为零，则使用0替代进行计算。",
    "总院住院费用表-人均住院费用": "总院住院费用表中的人均住院费用通过将总院总费用除以总院住院人数来计算。",
    "病案首页基本信息表-门急诊挂号人次": "病案首页基本信息表中的门急诊挂号人次是指病案首页基本信息表中记录的门诊人次与急诊人次的总和。",
    "住院工作量-床位使用率": "住院工作量-床位使用率通过将实际占用床位数合计除以开放床数合计来计算，若分母或分子为null，则使用coalesce函数替换为0以避免除零错误。",
    "住院工作量-床均出院人数": "住院工作量-床均出院人数通过将住院工作量中的出院人数总和除以开放床位总数来计算，反映单位时间内每张床位平均服务的出院人数。",
    "病案首页基本信息表-混合人次测试": "病案首页基本信息表中的混合人次测试旨在评估并统计在特定时间段内，既符合住院标准又符合门诊标准的患者人次。此测试通过分析病案首页数据，确保每位患者仅被计数一次，无论其在住院和门诊之间如何流动。",
    "看板记录-null数量": "衡量系统中看板记录中null值的数量，用于评估数据完整性和准确性。",
    "看板记录-应用标识数量": "表示应用标识数量的看板记录，指的是在特定时间范围内，系统中记录的应用程序标识总数。",
    "看板记录-报表名称数量": "看板记录-报表名称数量 指的是统计在看板系统中，所有被记录的报表名称的总数，反映的是当前系统内存在的报表种类的丰富程度或多样性。",
    "看板记录-null合计": "表示看板记录中null值的总和，即统计所有看板记录里出现的null值数量的总计。",
    "看板记录-null平均": "看板记录-null平均 指标衡量的是在特定时间段内，看板系统中记录为空或缺失值的平均数量。此指标用于评估系统数据完整性和记录准确性，帮助识别潜在的数据录入或维护问题。",
    "看板记录-null最小值": "表示看板记录中null值的最小数量，用于衡量数据记录中缺失值的最少分布情况。",
    "看板记录-null最大值": "表示看板记录中null值的最大数量，用于评估数据完整性和记录质量。",
    "看板记录-看板类型数量": "衡量在特定时间段内，不同类型的看板记录的总数，反映看板类型的多样性与使用频率。",
    "看板记录-创建日期数量": "表示在特定时间段内，看板记录被创建的数量。",
    "看板记录-修改日期数量": "表示在一定周期内，看板记录被修改的次数，反映看板内容更新频率。",
    "病案首页基本信息表-混合测试2": "病案首页基本信息表-混合测试2 指标用于评估病案首页中基本信息表的准确性和完整性，通过混合测试2来确保各项数据字段符合标准要求，包括但不限于患者基本信息、诊断信息、治疗信息等，旨在提高医疗记录的质量和可靠性。",
    "总院住院费用表-分析维度测试指标": "总院住院费用表的分析维度测试指标旨在评估住院费用在不同维度上的分布情况，通过设定特定规则来确保数据的准确性和全面性，从而为医院管理提供决策支持。规则包括但不限于不允许使用特定话术，以保持描述的专业性和客观性。",
    "总院住院费用表-费用总额": "总院住院费用表中的费用总额指标反映的是患者在住院期间所产生的所有费用的累计总和，包括但不限于床位费、诊疗费、药品费、检查费等各项费用的总和。",
    "总院住院费用表-混合费用": "总院住院费用表中的混合费用指标，反映的是在特定时间段内，医院住院患者所产生的一系列费用的总和，包括但不限于药品费、治疗费、护理费、检查费等各项费用的合计。",
    "总院住院费用表-统筹费用": "总院住院费用表中的统筹费用指标反映的是在特定时间段内，由医疗保险统筹基金支付的住院费用总额，涵盖所有符合报销条件的住院治疗费用。",
    "总院住院费用表-费用总和": "总院住院费用表中的费用总和指标用于衡量特定时间段内，所有住院患者在总院产生的医疗费用的累计总额。",
    "主键合计-aaaa": "主键合计-aaaa 指的是根据特定规则计算出的主键总数，通常用于衡量数据表中唯一标识记录的数量。",
    "总院住院费用表-费用总和测试": "总院住院费用表中的费用总和测试旨在评估所有住院费用的累计总额，确保数据的完整性和准确性。此测试通过检查各项费用是否正确累加，来验证住院费用记录的精确性。",
    "病案首页基本信息表-指标名称重复": "病案首页基本信息表中的指标名称重复指的是在病案首页基本信息表中，不允许出现相同名称的指标。",
    "总院住院费用表-费用名称重复": "总院住院费用表中，费用名称重复的指标用于衡量费用名称在数据集中出现重复的频率或次数，确保每个费用名称在记录中唯一，避免数据冗余和混淆。",
    "十梓街住院费用表-费用名称重复": "十梓街住院费用表中，费用名称重复的指标用于衡量费用名称在数据集中出现重复的频率或次数，确保每个费用名称在表中唯一，避免数据冗余和混淆。",
    "病案首页基本信息表-住院医师数量1": "统计“病案首页基本信息表”中“住院医师”的记录数量，计算该表内所有标记为“住院医师”的条目总数。",
    "分公司经营情况表-分公司编码数量": "分公司经营情况表中的分公司编码数量指标反映的是在特定时间段内，分公司所拥有的唯一编码的数量，用于衡量分公司的规模或管理的复杂度。",
    "分公司经营情况表-分公司名称数量": "分公司经营情况表中的分公司名称数量指标反映的是在特定时间段内，分公司经营情况表中所记录的不同分公司名称的总数，用于衡量分公司覆盖的范围或数量。",
    "分公司经营情况表-分公司部门经营数据合计": "分公司经营情况表中的分公司部门经营数据合计，反映了特定时期内分公司各部门在收入、成本、利润等方面的汇总情况，用于评估分公司整体的经营状况和各部门的业绩表现。",
    "分公司经营情况表-分公司部门经营数据平均": "分公司经营情况表中的分公司部门经营数据平均，表示通过汇总各分公司部门的经营数据，并计算其平均值，以此来反映各分公司部门整体的经营状况。",
    "分公司经营情况表-分公司部门经营数据最小值": "分公司经营情况表中分公司部门经营数据的最小值反映了各分公司部门在经营数据上的最低表现水平，用于评估分公司内部各部门经营状况的下限。",
    "分公司经营情况表-分公司部门经营数据最大值": "分公司经营情况表中的分公司部门经营数据最大值，表示在所有分公司部门的经营数据中，数值最大的那个数据点，反映了分公司内部经营表现的最佳水平。",
    "分公司经营情况表-采购部门编码数量": "分公司经营情况表中的采购部门编码数量指标，用于衡量特定时期内分公司采购部门所使用的编码数量，反映采购活动的活跃程度及管理效率。",
    "分公司经营情况表-营销部门编码数量": "分公司经营情况表中的营销部门编码数量反映了营销部门内部使用的唯一标识符总数，这些编码用于区分不同的营销活动或项目。",
    "营销部门表-部门编码数量": "营销部门表中包含的部门编码数量，即统计该表内所有不同的部门编码的总数。",
    "营销部门表-部门名称数量": "营销部门表中不同部门名称的数量，反映了营销部门内部结构的多样性，即统计营销部门表内所有唯一部门名称的总数。",
    "营销部门表-更新日期数量": "营销部门表中记录了更新日期的数量，即统计营销部门表内所有不同日期更新记录的总数。",
    "经营成本表-公司编码数量": "经营成本表中的公司编码数量指标用于反映在特定时间段内，与经营成本相关的不同公司编码的数量，以此来衡量涉及经营成本的公司范围或规模。",
    "经营成本表-公司名称数量": "经营成本表中记录了特定时间段内与公司经营相关的成本数据，公司名称数量指标反映的是在此期间内涉及经营成本的公司总数。",
    "经营成本表-公司经营成本合计": "经营成本表-公司经营成本合计反映了一家公司在一个特定时期内所有与经营直接相关的成本总和，包括但不限于原材料成本、人工成本、租金、折旧、维修费用及其他运营开支。",
    "经营成本表-公司经营成本平均": "经营成本表-公司经营成本平均 指的是通过计算一定时期内公司经营成本的总和并除以该时期内的经营次数或时间单位，得出的平均经营成本数值，用于反映公司在特定时间段内的平均经营成本水平。",
    "经营成本表-公司经营成本最小值": "展示了公司在特定时间段内经营成本的最低值，反映公司运营效率和成本控制能力的最佳表现。",
    "经营成本表-公司经营成本最大值": "展示了公司在特定时间段内经营成本的最大值，用于评估公司运营期间成本控制的最不利情况。",
    "经营成本表-记录日期数量": "经营成本表中记录的日期数量，指的是在特定时间段内，经营成本表中包含的不同日期的数量统计，用于反映记录的完整性和时间跨度。",
    "采购部门表-部门编码数量": "采购部门表中包含的部门编码数量，即统计该表内所有不同的部门编码的总数。",
    "采购部门表-部门名称数量": "采购部门表中不同部门名称的数量，即统计采购部门表内所有部门名称的种类数目。",
    "采购部门表-更新日期数量": "采购部门表的更新日期数量指的是统计在特定时间段内，采购部门相关数据表中记录的更新日期的总次数。"
}